cator/__init__.py
cator/common.py
cator/db_url.py
cator/logger.py
cator/version.py
cator/base/__init__.py
cator/base/collection.py
cator/base/connection.py
cator/base/database.py
cator/base/dbapi.py
cator/base/query.py
cator/base/reconnect_mixin.py
cator/base/table.py
cator/mysql/__init__.py
cator/mysql/database.py
cator/sql/__init__.py
cator/sql/sql_builder.py
cator/sql/sql_util.py
cator/sqlite/__init__.py
cator/sqlite/database.py
tests/__init__.py
tests/mysql_database_test.py
tests/peewee_database_test.py
tests/pymysql_test.py
tests/sql_builder_test.py
tests/sqlite_database_test.py
tests/test_hello.py
cator-1.0.11.dist-info/METADATA
cator-1.0.11.dist-info/WHEEL
cator-1.0.11.dist-info/top_level.txt
cator-1.0.11.dist-info/zip-safe
cator-1.0.11.dist-info/RECORD
