Metadata-Version: 2.1
Name: cator
Version: 1.0.11
Summary: a quick tool base dict for mysql and sqlite
Home-page: https://github.com/mouday/cator
Author: Peng Shiyu
Author-email: pengshiyuyx@gmail.com
License: MIT
Keywords: cator,mysql,pymysql,sqlite,dict,peewee
Classifier: Programming Language :: Python :: 3
Classifier: Programming Language :: Python :: 3.5
Classifier: Programming Language :: Python :: 3.7
Classifier: Programming Language :: Python :: 3.8
Classifier: Programming Language :: Python :: 3.9
Classifier: Programming Language :: Python :: 3.10
Classifier: Programming Language :: Python :: 3.11
